recolul/__init__.py
recolul/cli.py
recolul/config.py
recolul/duration.py
recolul/errors.py
recolul/plotting.py
recolul/time.py
recolul/recoru/__init__.py
recolul/recoru/attendance_chart.py
recolul/recoru/recoru_session.py
recolul-1.20.0.dist-info/LICENSE
recolul-1.20.0.dist-info/METADATA
recolul-1.20.0.dist-info/WHEEL
recolul-1.20.0.dist-info/entry_points.txt
recolul-1.20.0.dist-info/top_level.txt
recolul-1.20.0.dist-info/RECORD
