Metadata-Version: 2.1
Name: recolul
Version: 1.20.0
Summary: Overtime management for RecoRu
Home-page: https://github.com/Maerig/recolul
Author: Jean-Loup Roussel-Clouet
Author-email: jean-loup@cryptact.com
Classifier: Programming Language :: Python :: 3
Classifier: Operating System :: OS Independent
Requires-Python: >=3.10
License-File: LICENSE
Requires-Dist: beautifulsoup4~=4.11
Requires-Dist: plotly~=5.18
Requires-Dist: requests~=2.31
Provides-Extra: dev
Requires-Dist: build~=1.0.3; extra == "dev"
Requires-Dist: pytest~=7.4; extra == "dev"
Requires-Dist: twine~=5.1.1; extra == "dev"
Provides-Extra: gui
Requires-Dist: pyside6~=6.7.0; extra == "gui"
